{
   "status" : "ok",
   "entry" : {
      "rows" : [
         {
            "id" : "1",
            "name" : "molon1",
            "avatar" : "http://molon.me/avatar.jpg"
         },
         {
            "name" : "molon2",
            "id" : "2",
            "avatar" : "http://molon.me/avatar.jpg"
         },
         {
            "id" : "3",
            "name" : "molon3",
            "avatar" : "http://molon.me/avatar.jpg"
         },
         {
            "name" : "molon4",
            "id" : "4",
            "avatar" : "http://molon.me/avatar.jpg"
         },
         {
            "id" : "5",
            "name" : "molon5",
            "avatar" : "http://molon.me/avatar.jpg"
         },
         {
            "name" : "molon6",
            "id" : "6",
            "avatar" : "http://molon.me/avatar.jpg"
         },
         {
            "avatar" : "http://molon.me/avatar.jpg",
            "id" : "7",
            "name" : "molon7"
         },
         {
            "avatar" : "http://molon.me/avatar.jpg",
            "name" : "molon8",
            "id" : "8"
         },
         {
            "name" : "molon9",
            "id" : "9",
            "avatar" : "http://molon.me/avatar.jpg"
         },
         {
            "name" : "molon_t",
            "id" : "10",
            "avatar" : "http://molon.me/avatar.jpg"
         },
         {
            "name" : "molon11",
            "id" : "11",
            "avatar" : "http://molon.me/avatar.jpg"
         },
         {
            "id" : "12",
            "name" : "molon12",
            "avatar" : "http://molon.me/avatar.jpg"
         },
         {
            "avatar" : "http://molon.me/avatar.jpg",
            "name" : "molon13",
            "id" : "13"
         },
         {
            "id" : "14",
            "name" : "molon14",
            "avatar" : "http://molon.me/avatar.jpg"
         },
         {
            "name" : "molon15",
            "id" : "15",
            "avatar" : "http://molon.me/avatar.jpg"
         },
         {
            "avatar" : "http://molon.me/avatar.jpg",
            "id" : "111",
            "name" : "molon111"
         }
      ]
   }
}